beret/__init__.py
beret/__init__tmp.py
beret/annotate/AminoAcidEdit.py
beret/annotate/__init__.py
beret/annotate/translate_allele.py
beret/framework/Edit.py
beret/framework/ReporterScreen.py
beret/framework/__init__.py
beret/framework/_supporting_fn.py
beret/framework/filter_alleles.py
beret/preprocessing/CRISPResso2Align.c
beret/preprocessing/CRISPResso2Align.cpython-38-x86_64-linux-gnu.so
beret/preprocessing/CRISPResso2Align.pyx
beret/preprocessing/GuideEditCounter.py
beret/preprocessing/Step1_count_gRNA.py
beret/preprocessing/__init__.py
beret/preprocessing/_supporting_fn.py
beret/preprocessing/utils.py
beret/utils/__init__.py
beret/utils/arithmetric.py
berets-0.1.2.data/scripts/beret-count
berets-0.1.2.data/scripts/beret-count-samples
berets-0.1.2.dist-info/METADATA
berets-0.1.2.dist-info/WHEEL
berets-0.1.2.dist-info/top_level.txt
berets-0.1.2.dist-info/RECORD
