Metadata-Version: 2.1
Name: berets
Version: 0.1.2
Summary: Tools for analyzing CRISPR data with REPorter edits
Home-page: https://github.com/pinellolab/beret
Author: Jayoung Ryu
Author-email: jayoung_ryu@g.harvard.edu
License: UNKNOWN
Platform: UNKNOWN
Classifier: Programming Language :: Python :: 3
Classifier: Operating System :: OS Independent
Requires-Dist: numpy
Requires-Dist: perturb-tools (>=0.0.16)
